[
  {
    "currency": "USDKRW",
    "rates": [
      {
        "date": "20251217",
        "open": 1472.4,
        "high": 1487.12,
        "low": 1457.67,
        "close": 1472.4
      },
      {
        "date": "20251218",
        "open": 1472.4,
        "high": 1493.38,
        "low": 1463.81,
        "close": 1478.6
      },
      {
        "date": "20251219",
        "open": 1478.6,
        "high": 1491.97,
        "low": 1462.42,
        "close": 1477.2
      },
      {
        "date": "20251222",
        "open": 1477.2,
        "high": 1492.57,
        "low": 1463.02,
        "close": 1477.8
      },
      {
        "date": "20251223",
        "open": 1477.8,
        "high": 1493.68,
        "low": 1464.11,
        "close": 1478.9
      },
      {
        "date": "20251224",
        "open": 1478.9,
        "high": 1498.23,
        "low": 1468.56,
        "close": 1483.4
      },
      {
        "date": "20251226",
        "open": 1483.4,
        "high": 1475.2,
        "low": 1445.99,
        "close": 1460.6
      },
      {
        "date": "20251229",
        "open": 1460.6,
        "high": 1456.72,
        "low": 1427.87,
        "close": 1442.3
      },
      {
        "date": "20251230",
        "open": 1442.3,
        "high": 1448.23,
        "low": 1419.56,
        "close": 1433.9
      },
      {
        "date": "20251231",
        "open": 1433.9,
        "high": 1449.24,
        "low": 1420.55,
        "close": 1434.9
      },
      {
        "date": "20260102",
        "open": 1434.9,
        "high": 1449.24,
        "low": 1420.55,
        "close": 1434.9
      },
      {
        "date": "20260105",
        "open": 1434.9,
        "high": 1456.52,
        "low": 1427.67,
        "close": 1442.1
      },
      {
        "date": "20260106",
        "open": 1442.1,
        "high": 1461.26,
        "low": 1432.33,
        "close": 1446.8
      },
      {
        "date": "20260107",
        "open": 1446.8,
        "high": 1460.15,
        "low": 1431.24,
        "close": 1445.7
      },
      {
        "date": "20260108",
        "open": 1445.7,
        "high": 1462.78,
        "low": 1433.81,
        "close": 1448.3
      },
      {
        "date": "20260109",
        "open": 1448.3,
        "high": 1463.89,
        "low": 1434.9,
        "close": 1449.4
      },
      {
        "date": "20260112",
        "open": 1449.4,
        "high": 1470.25,
        "low": 1441.14,
        "close": 1455.7
      },
      {
        "date": "20260113",
        "open": 1455.7,
        "high": 1478.74,
        "low": 1449.45,
        "close": 1464.1
      },
      {
        "date": "20260114",
        "open": 1464.1,
        "high": 1487.52,
        "low": 1458.07,
        "close": 1472.8
      },
      {
        "date": "20260115",
        "open": 1472.8,
        "high": 1492.27,
        "low": 1462.72,
        "close": 1477.5
      },
      {
        "date": "20260116",
        "open": 1477.5,
        "high": 1484.39,
        "low": 1455,
        "close": 1469.7
      },
      {
        "date": "20260119",
        "open": 1469.7,
        "high": 1488.23,
        "low": 1458.76,
        "close": 1473.5
      },
      {
        "date": "20260120",
        "open": 1473.5,
        "high": 1488.33,
        "low": 1458.86,
        "close": 1473.6
      },
      {
        "date": "20260121",
        "open": 1473.6,
        "high": 1491.77,
        "low": 1462.23,
        "close": 1477
      },
      {
        "date": "20260122",
        "open": 1477,
        "high": 1487.52,
        "low": 1458.07,
        "close": 1472.8
      },
      {
        "date": "20260123",
        "open": 1472.8,
        "high": 1483.08,
        "low": 1453.71,
        "close": 1468.4
      },
      {
        "date": "20260126",
        "open": 1468.4,
        "high": 1481.87,
        "low": 1452.52,
        "close": 1467.2
      },
      {
        "date": "20260127",
        "open": 1467.2,
        "high": 1457.22,
        "low": 1428.37,
        "close": 1442.8
      },
      {
        "date": "20260128",
        "open": 1442.8,
        "high": 1463.28,
        "low": 1434.31,
        "close": 1448.8
      },
      {
        "date": "20260129",
        "open": 1448.8,
        "high": 1442.88,
        "low": 1414.31,
        "close": 1428.6
      },
      {
        "date": "20260130",
        "open": 1428.6,
        "high": 1441.27,
        "low": 1412.73,
        "close": 1427
      },
      {
        "date": "20260202",
        "open": 1427,
        "high": 1451.06,
        "low": 1422.33,
        "close": 1436.7
      },
      {
        "date": "20260203",
        "open": 1436.7,
        "high": 1471.87,
        "low": 1442.72,
        "close": 1457.3
      },
      {
        "date": "20260204",
        "open": 1457.3,
        "high": 1463.49,
        "low": 1434.51,
        "close": 1449
      },
      {
        "date": "20260205",
        "open": 1449,
        "high": 1465.71,
        "low": 1436.68,
        "close": 1451.2
      },
      {
        "date": "20260206",
        "open": 1451.2,
        "high": 1478.74,
        "low": 1449.45,
        "close": 1464.1
      },
      {
        "date": "20260209",
        "open": 1464.1,
        "high": 1485,
        "low": 1455.59,
        "close": 1470.3
      },
      {
        "date": "20260210",
        "open": 1470.3,
        "high": 1478.94,
        "low": 1449.65,
        "close": 1464.3
      },
      {
        "date": "20260211",
        "open": 1464.3,
        "high": 1472.27,
        "low": 1443.12,
        "close": 1457.7
      },
      {
        "date": "20260212",
        "open": 1457.7,
        "high": 1468.94,
        "low": 1439.85,
        "close": 1454.4
      },
      {
        "date": "20260213",
        "open": 1454.4,
        "high": 1457.83,
        "low": 1428.96,
        "close": 1443.4
      },
      {
        "date": "20260219",
        "open": 1443.4,
        "high": 1457.53,
        "low": 1428.66,
        "close": 1443.1
      },
      {
        "date": "20260220",
        "open": 1443.1,
        "high": 1465.2,
        "low": 1436.19,
        "close": 1450.7
      },
      {
        "date": "20260223",
        "open": 1450.7,
        "high": 1463.18,
        "low": 1434.21,
        "close": 1448.7
      },
      {
        "date": "20260224",
        "open": 1448.7,
        "high": 1456.42,
        "low": 1427.58,
        "close": 1442
      },
      {
        "date": "20260225",
        "open": 1442,
        "high": 1460.25,
        "low": 1431.34,
        "close": 1445.8
      },
      {
        "date": "20260226",
        "open": 1445.8,
        "high": 1449.65,
        "low": 1420.94,
        "close": 1435.3
      },
      {
        "date": "20260227",
        "open": 1435.3,
        "high": 1438.74,
        "low": 1410.25,
        "close": 1424.5
      },
      {
        "date": "20260303",
        "open": 1424.5,
        "high": 1449.75,
        "low": 1421.04,
        "close": 1435.4
      },
      {
        "date": "20260304",
        "open": 1435.4,
        "high": 1479.14,
        "low": 1449.85,
        "close": 1464.5
      },
      {
        "date": "20260305",
        "open": 1464.5,
        "high": 1493.58,
        "low": 1464.01,
        "close": 1478.8
      },
      {
        "date": "20260306",
        "open": 1478.8,
        "high": 1478.94,
        "low": 1449.65,
        "close": 1464.3
      },
      {
        "date": "20260309",
        "open": 1464.3,
        "high": 1489.24,
        "low": 1459.75,
        "close": 1474.5
      },
      {
        "date": "20260310",
        "open": 1474.5,
        "high": 1508.03,
        "low": 1478.16,
        "close": 1493.1
      },
      {
        "date": "20260311",
        "open": 1493.1,
        "high": 1487.52,
        "low": 1458.07,
        "close": 1472.8
      },
      {
        "date": "20260312",
        "open": 1472.8,
        "high": 1481.97,
        "low": 1452.62,
        "close": 1467.3
      },
      {
        "date": "20260313",
        "open": 1467.3,
        "high": 1494.59,
        "low": 1465,
        "close": 1479.8
      },
      {
        "date": "20260316",
        "open": 1479.8,
        "high": 1504.39,
        "low": 1474.6,
        "close": 1489.5
      },
      {
        "date": "20260317",
        "open": 1489.5,
        "high": 1510.96,
        "low": 1481.04,
        "close": 1496
      },
      {
        "date": "20260318",
        "open": 1496,
        "high": 1506.51,
        "low": 1476.68,
        "close": 1491.6
      },
      {
        "date": "20260319",
        "open": 1491.6,
        "high": 1500.86,
        "low": 1471.14,
        "close": 1486
      },
      {
        "date": "20260320",
        "open": 1486,
        "high": 1514.69,
        "low": 1484.7,
        "close": 1499.7
      }
    ],
    "signal": {
      "currency": "USDKRW",
      "signal": "BUY",
      "strength": "MODERATE",
      "score": 47,
      "indicators": [
        {
          "name": "RSI(14)",
          "value": 61.15361345271601,
          "signal": "SELL",
          "description": "약한 과매수 (61.2)"
        },
        {
          "name": "EMA(5/20)",
          "value": 16.857824476554697,
          "signal": "BUY",
          "description": "단기 > 장기 (1491.1 > 1474.2)"
        },
        {
          "name": "MACD(12/26/9)",
          "value": 3.3239035319033103,
          "signal": "BUY",
          "description": "히스토그램 양(+3.32)"
        },
        {
          "name": "Bollinger(20/2)",
          "value": 0.8662502627057037,
          "signal": "SELL",
          "description": "상단 근접 (위치: 87%)"
        },
        {
          "name": "ADX(14)",
          "value": 15.7255,
          "signal": "NEUTRAL",
          "description": "횡보 (ADX 15.7 < 20) — 추세 신호 신뢰도 낮음"
        },
        {
          "name": "EMA(60) 추세",
          "value": 2.599568418666715,
          "signal": "BUY",
          "description": "장기 상승 추세 (현재 2.60% > EMA60)"
        },
        {
          "name": "신호 연속성",
          "value": 20,
          "signal": "BUY",
          "description": "전일 방향 일치 (+10)"
        },
        {
          "name": "VIX 공포지수",
          "value": 26.780000686645508,
          "signal": "BUY",
          "description": "리스크 오프 (VIX 26.8) — 외화 강세 우위"
        },
        {
          "name": "US10Y 국채금리",
          "value": 4.390999794006348,
          "signal": "BUY",
          "description": "미국채 10Y 금리 상승 (+0.25%) → USD 강세"
        }
      ],
      "currentRate": 1499.7,
      "targetBuy": 1467.99,
      "targetSell": 1544.1,
      "targetBuyEffective": 1493.68,
      "targetSellEffective": 1517.07,
      "stopLoss": 1480.67,
      "spreadPct": 1.75,
      "effectiveBuyRate": 1525.94,
      "effectiveSellRate": 1473.46,
      "breakEvenPct": 3.5,
      "netProfitPct": 1.57,
      "calculatedAt": "2026-03-22T18:45:22.669Z"
    },
    "macro": {
      "vix": 26.780000686645508,
      "vixPrev": 25.5,
      "us10y": 4.390999794006348,
      "us10yPrev": 4.136000156402588,
      "fetchedAt": "2026-03-22T18:45:21.555Z"
    },
    "updatedAt": "2026-03-22T18:45:22.669Z"
  },
  {
    "currency": "EURKRW",
    "rates": [
      {
        "date": "20251217",
        "open": 1730,
        "high": 1747.3,
        "low": 1712.7,
        "close": 1730
      },
      {
        "date": "20251218",
        "open": 1730,
        "high": 1753.53,
        "low": 1718.8,
        "close": 1736.17
      },
      {
        "date": "20251219",
        "open": 1736.17,
        "high": 1749.48,
        "low": 1714.83,
        "close": 1732.16
      },
      {
        "date": "20251222",
        "open": 1732.16,
        "high": 1748.33,
        "low": 1713.7,
        "close": 1731.02
      },
      {
        "date": "20251223",
        "open": 1731.02,
        "high": 1757.17,
        "low": 1722.38,
        "close": 1739.78
      },
      {
        "date": "20251224",
        "open": 1739.78,
        "high": 1767.23,
        "low": 1732.24,
        "close": 1749.74
      },
      {
        "date": "20251226",
        "open": 1749.74,
        "high": 1738.31,
        "low": 1703.88,
        "close": 1721.1
      },
      {
        "date": "20251229",
        "open": 1721.1,
        "high": 1715.43,
        "low": 1681.46,
        "close": 1698.45
      },
      {
        "date": "20251230",
        "open": 1698.45,
        "high": 1705.23,
        "low": 1671.46,
        "close": 1688.35
      },
      {
        "date": "20251231",
        "open": 1688.35,
        "high": 1702.57,
        "low": 1668.86,
        "close": 1685.72
      },
      {
        "date": "20260102",
        "open": 1685.72,
        "high": 1702.57,
        "low": 1668.86,
        "close": 1685.72
      },
      {
        "date": "20260105",
        "open": 1685.72,
        "high": 1705.87,
        "low": 1672.1,
        "close": 1688.99
      },
      {
        "date": "20260106",
        "open": 1688.99,
        "high": 1712.45,
        "low": 1678.54,
        "close": 1695.5
      },
      {
        "date": "20260107",
        "open": 1695.5,
        "high": 1706.84,
        "low": 1673.05,
        "close": 1689.95
      },
      {
        "date": "20260108",
        "open": 1689.95,
        "high": 1708.09,
        "low": 1674.26,
        "close": 1691.18
      },
      {
        "date": "20260109",
        "open": 1691.18,
        "high": 1706.9,
        "low": 1673.1,
        "close": 1690
      },
      {
        "date": "20260112",
        "open": 1690,
        "high": 1710.35,
        "low": 1676.48,
        "close": 1693.42
      },
      {
        "date": "20260113",
        "open": 1693.42,
        "high": 1725.17,
        "low": 1691,
        "close": 1708.09
      },
      {
        "date": "20260114",
        "open": 1708.09,
        "high": 1732.15,
        "low": 1697.85,
        "close": 1715
      },
      {
        "date": "20260115",
        "open": 1715,
        "high": 1737.82,
        "low": 1703.41,
        "close": 1720.62
      },
      {
        "date": "20260116",
        "open": 1720.62,
        "high": 1723.16,
        "low": 1689.03,
        "close": 1706.1
      },
      {
        "date": "20260119",
        "open": 1706.1,
        "high": 1726.64,
        "low": 1692.45,
        "close": 1709.55
      },
      {
        "date": "20260120",
        "open": 1709.55,
        "high": 1732.94,
        "low": 1698.63,
        "close": 1715.79
      },
      {
        "date": "20260121",
        "open": 1715.79,
        "high": 1749.02,
        "low": 1714.39,
        "close": 1731.71
      },
      {
        "date": "20260122",
        "open": 1731.71,
        "high": 1738.09,
        "low": 1703.68,
        "close": 1720.89
      },
      {
        "date": "20260123",
        "open": 1720.89,
        "high": 1743.88,
        "low": 1709.35,
        "close": 1726.62
      },
      {
        "date": "20260126",
        "open": 1726.62,
        "high": 1761.5,
        "low": 1726.61,
        "close": 1744.06
      },
      {
        "date": "20260127",
        "open": 1744.06,
        "high": 1731.03,
        "low": 1696.76,
        "close": 1713.9
      },
      {
        "date": "20260128",
        "open": 1713.9,
        "high": 1760.48,
        "low": 1725.61,
        "close": 1743.05
      },
      {
        "date": "20260129",
        "open": 1743.05,
        "high": 1724.82,
        "low": 1690.67,
        "close": 1707.75
      },
      {
        "date": "20260130",
        "open": 1707.75,
        "high": 1725.41,
        "low": 1691.24,
        "close": 1708.33
      },
      {
        "date": "20260202",
        "open": 1708.33,
        "high": 1718.21,
        "low": 1684.18,
        "close": 1701.2
      },
      {
        "date": "20260203",
        "open": 1701.2,
        "high": 1735.77,
        "low": 1701.4,
        "close": 1718.59
      },
      {
        "date": "20260204",
        "open": 1718.59,
        "high": 1729.62,
        "low": 1695.37,
        "close": 1712.5
      },
      {
        "date": "20260205",
        "open": 1712.5,
        "high": 1730.56,
        "low": 1696.29,
        "close": 1713.43
      },
      {
        "date": "20260206",
        "open": 1713.43,
        "high": 1741.73,
        "low": 1707.24,
        "close": 1724.49
      },
      {
        "date": "20260209",
        "open": 1724.49,
        "high": 1754.08,
        "low": 1719.35,
        "close": 1736.72
      },
      {
        "date": "20260210",
        "open": 1736.72,
        "high": 1761.41,
        "low": 1726.54,
        "close": 1743.98
      },
      {
        "date": "20260211",
        "open": 1743.98,
        "high": 1750.61,
        "low": 1715.94,
        "close": 1733.28
      },
      {
        "date": "20260212",
        "open": 1733.28,
        "high": 1743.85,
        "low": 1709.32,
        "close": 1726.59
      },
      {
        "date": "20260213",
        "open": 1726.59,
        "high": 1730.52,
        "low": 1696.25,
        "close": 1713.39
      },
      {
        "date": "20260219",
        "open": 1713.39,
        "high": 1718.28,
        "low": 1684.25,
        "close": 1701.27
      },
      {
        "date": "20260220",
        "open": 1701.27,
        "high": 1725.21,
        "low": 1691.04,
        "close": 1708.13
      },
      {
        "date": "20260223",
        "open": 1708.13,
        "high": 1726.56,
        "low": 1692.37,
        "close": 1709.47
      },
      {
        "date": "20260224",
        "open": 1709.47,
        "high": 1717.26,
        "low": 1683.25,
        "close": 1700.26
      },
      {
        "date": "20260225",
        "open": 1700.26,
        "high": 1719.3,
        "low": 1685.25,
        "close": 1702.28
      },
      {
        "date": "20260226",
        "open": 1702.28,
        "high": 1712.54,
        "low": 1678.63,
        "close": 1695.59
      },
      {
        "date": "20260227",
        "open": 1695.59,
        "high": 1697.5,
        "low": 1663.89,
        "close": 1680.7
      },
      {
        "date": "20260303",
        "open": 1680.7,
        "high": 1695.26,
        "low": 1661.69,
        "close": 1678.48
      },
      {
        "date": "20260304",
        "open": 1678.48,
        "high": 1718.1,
        "low": 1684.07,
        "close": 1701.09
      },
      {
        "date": "20260305",
        "open": 1701.09,
        "high": 1737.78,
        "low": 1703.37,
        "close": 1720.58
      },
      {
        "date": "20260306",
        "open": 1720.58,
        "high": 1716.53,
        "low": 1682.54,
        "close": 1699.54
      },
      {
        "date": "20260309",
        "open": 1699.54,
        "high": 1717.84,
        "low": 1683.83,
        "close": 1700.84
      },
      {
        "date": "20260310",
        "open": 1700.84,
        "high": 1753.84,
        "low": 1719.11,
        "close": 1736.48
      },
      {
        "date": "20260311",
        "open": 1736.48,
        "high": 1726.57,
        "low": 1692.38,
        "close": 1709.48
      },
      {
        "date": "20260312",
        "open": 1709.48,
        "high": 1711.45,
        "low": 1677.56,
        "close": 1694.51
      },
      {
        "date": "20260313",
        "open": 1694.51,
        "high": 1721.77,
        "low": 1687.68,
        "close": 1704.73
      },
      {
        "date": "20260316",
        "open": 1704.73,
        "high": 1719.74,
        "low": 1685.69,
        "close": 1702.72
      },
      {
        "date": "20260317",
        "open": 1702.72,
        "high": 1737.23,
        "low": 1702.82,
        "close": 1720.03
      },
      {
        "date": "20260318",
        "open": 1720.03,
        "high": 1738.44,
        "low": 1704.01,
        "close": 1721.23
      },
      {
        "date": "20260319",
        "open": 1721.23,
        "high": 1719.68,
        "low": 1685.63,
        "close": 1702.66
      },
      {
        "date": "20260320",
        "open": 1702.66,
        "high": 1753.94,
        "low": 1719.21,
        "close": 1736.58
      }
    ],
    "signal": {
      "currency": "EURKRW",
      "signal": "BUY",
      "strength": "MODERATE",
      "score": 35,
      "indicators": [
        {
          "name": "RSI(14)",
          "value": 56.764422406398666,
          "signal": "NEUTRAL",
          "description": "중립 (56.8)"
        },
        {
          "name": "EMA(5/20)",
          "value": 7.330116795224967,
          "signal": "BUY",
          "description": "단기 > 장기 (1718.8 > 1711.5)"
        },
        {
          "name": "MACD(12/26/9)",
          "value": 2.6944601994309334,
          "signal": "BUY",
          "description": "히스토그램 양(+2.69)"
        },
        {
          "name": "Bollinger(20/2)",
          "value": 1.014803681784569,
          "signal": "SELL",
          "description": "상단 터치 (현재: 1736.6, 상단: 1735.7)"
        },
        {
          "name": "ADX(14)",
          "value": 8.8791,
          "signal": "NEUTRAL",
          "description": "횡보 (ADX 8.9 < 20) — 추세 신호 신뢰도 낮음"
        },
        {
          "name": "EMA(60) 추세",
          "value": 1.3960568581834887,
          "signal": "BUY",
          "description": "장기 상승 추세 (현재 1.40% > EMA60)"
        },
        {
          "name": "신호 연속성",
          "value": 20,
          "signal": "BUY",
          "description": "전일 방향 일치 (+10)"
        },
        {
          "name": "VIX 공포지수",
          "value": 26.780000686645508,
          "signal": "BUY",
          "description": "리스크 오프 (VIX 26.8) — 외화 강세 우위"
        }
      ],
      "currentRate": 1736.58,
      "targetBuy": 1693.26,
      "targetSell": 1797.23,
      "targetBuyEffective": 1722.89,
      "targetSellEffective": 1765.78,
      "stopLoss": 1710.59,
      "spreadPct": 1.75,
      "effectiveBuyRate": 1766.97,
      "effectiveSellRate": 1706.19,
      "breakEvenPct": 3.5,
      "netProfitPct": 2.49,
      "calculatedAt": "2026-03-22T18:45:23.701Z"
    },
    "macro": {
      "vix": 26.780000686645508,
      "vixPrev": 25.5,
      "us10y": 4.390999794006348,
      "us10yPrev": 4.136000156402588,
      "fetchedAt": "2026-03-22T18:45:21.555Z"
    },
    "updatedAt": "2026-03-22T18:45:23.701Z"
  },
  {
    "currency": "JPYKRW",
    "rates": [
      {
        "date": "20251217",
        "open": 951.47,
        "high": 960.98,
        "low": 941.95,
        "close": 951.47
      },
      {
        "date": "20251218",
        "open": 951.47,
        "high": 959.51,
        "low": 940.5,
        "close": 950.01
      },
      {
        "date": "20251219",
        "open": 950.01,
        "high": 959.12,
        "low": 940.13,
        "close": 949.63
      },
      {
        "date": "20251222",
        "open": 949.63,
        "high": 947.15,
        "low": 928.4,
        "close": 937.78
      },
      {
        "date": "20251223",
        "open": 937.78,
        "high": 951.57,
        "low": 932.72,
        "close": 942.15
      },
      {
        "date": "20251224",
        "open": 942.15,
        "high": 959.51,
        "low": 940.5,
        "close": 950.01
      },
      {
        "date": "20251226",
        "open": 950.01,
        "high": 946.64,
        "low": 927.89,
        "close": 937.27
      },
      {
        "date": "20251229",
        "open": 937.27,
        "high": 930.98,
        "low": 912.55,
        "close": 921.77
      },
      {
        "date": "20251230",
        "open": 921.77,
        "high": 928.27,
        "low": 909.88,
        "close": 919.08
      },
      {
        "date": "20251231",
        "open": 919.08,
        "high": 926.8,
        "low": 908.45,
        "close": 917.63
      },
      {
        "date": "20260102",
        "open": 917.63,
        "high": 924.21,
        "low": 905.9,
        "close": 915.06
      },
      {
        "date": "20260105",
        "open": 915.06,
        "high": 928.98,
        "low": 910.59,
        "close": 919.79
      },
      {
        "date": "20260106",
        "open": 919.79,
        "high": 933.45,
        "low": 914.96,
        "close": 924.21
      },
      {
        "date": "20260107",
        "open": 924.21,
        "high": 932.29,
        "low": 913.82,
        "close": 923.06
      },
      {
        "date": "20260108",
        "open": 923.06,
        "high": 933.7,
        "low": 915.21,
        "close": 924.46
      },
      {
        "date": "20260109",
        "open": 924.46,
        "high": 933.12,
        "low": 914.65,
        "close": 923.89
      },
      {
        "date": "20260112",
        "open": 923.89,
        "high": 930.22,
        "low": 911.79,
        "close": 921.01
      },
      {
        "date": "20260113",
        "open": 921.01,
        "high": 934.87,
        "low": 916.36,
        "close": 925.62
      },
      {
        "date": "20260114",
        "open": 925.62,
        "high": 934.58,
        "low": 916.07,
        "close": 925.33
      },
      {
        "date": "20260115",
        "open": 925.33,
        "high": 942.8,
        "low": 924.13,
        "close": 933.47
      },
      {
        "date": "20260116",
        "open": 933.47,
        "high": 935.78,
        "low": 917.25,
        "close": 926.52
      },
      {
        "date": "20260119",
        "open": 926.52,
        "high": 943.92,
        "low": 925.23,
        "close": 934.58
      },
      {
        "date": "20260120",
        "open": 934.58,
        "high": 941.05,
        "low": 922.42,
        "close": 931.74
      },
      {
        "date": "20260121",
        "open": 931.74,
        "high": 943.35,
        "low": 924.66,
        "close": 934.01
      },
      {
        "date": "20260122",
        "open": 934.01,
        "high": 939.71,
        "low": 921.1,
        "close": 930.41
      },
      {
        "date": "20260123",
        "open": 930.41,
        "high": 936.29,
        "low": 917.74,
        "close": 927.02
      },
      {
        "date": "20260126",
        "open": 927.02,
        "high": 958.36,
        "low": 939.39,
        "close": 948.88
      },
      {
        "date": "20260127",
        "open": 948.88,
        "high": 945.05,
        "low": 926.34,
        "close": 935.7
      },
      {
        "date": "20260128",
        "open": 935.7,
        "high": 960.31,
        "low": 941.3,
        "close": 950.81
      },
      {
        "date": "20260129",
        "open": 950.81,
        "high": 940.63,
        "low": 922,
        "close": 931.32
      },
      {
        "date": "20260130",
        "open": 931.32,
        "high": 942.21,
        "low": 923.56,
        "close": 932.89
      },
      {
        "date": "20260202",
        "open": 932.89,
        "high": 933.25,
        "low": 914.76,
        "close": 924.01
      },
      {
        "date": "20260203",
        "open": 924.01,
        "high": 946.02,
        "low": 927.29,
        "close": 936.66
      },
      {
        "date": "20260204",
        "open": 936.66,
        "high": 939.49,
        "low": 920.88,
        "close": 930.19
      },
      {
        "date": "20260205",
        "open": 930.19,
        "high": 934.64,
        "low": 916.13,
        "close": 925.39
      },
      {
        "date": "20260206",
        "open": 925.39,
        "high": 941.78,
        "low": 923.13,
        "close": 932.46
      },
      {
        "date": "20260209",
        "open": 932.46,
        "high": 942.13,
        "low": 923.48,
        "close": 932.81
      },
      {
        "date": "20260210",
        "open": 932.81,
        "high": 948.27,
        "low": 929.5,
        "close": 938.89
      },
      {
        "date": "20260211",
        "open": 938.89,
        "high": 953.05,
        "low": 934.18,
        "close": 943.62
      },
      {
        "date": "20260212",
        "open": 943.62,
        "high": 958.78,
        "low": 939.79,
        "close": 949.29
      },
      {
        "date": "20260213",
        "open": 949.29,
        "high": 954.17,
        "low": 935.28,
        "close": 944.73
      },
      {
        "date": "20260219",
        "open": 944.73,
        "high": 941.95,
        "low": 923.3,
        "close": 932.63
      },
      {
        "date": "20260220",
        "open": 932.63,
        "high": 945.51,
        "low": 926.78,
        "close": 936.15
      },
      {
        "date": "20260223",
        "open": 936.15,
        "high": 944.9,
        "low": 926.19,
        "close": 935.55
      },
      {
        "date": "20260224",
        "open": 935.55,
        "high": 942.23,
        "low": 923.58,
        "close": 932.91
      },
      {
        "date": "20260225",
        "open": 932.91,
        "high": 936.93,
        "low": 918.38,
        "close": 927.66
      },
      {
        "date": "20260226",
        "open": 927.66,
        "high": 927.57,
        "low": 909.2,
        "close": 918.39
      },
      {
        "date": "20260227",
        "open": 918.39,
        "high": 922.51,
        "low": 904.24,
        "close": 913.38
      },
      {
        "date": "20260303",
        "open": 913.38,
        "high": 921.47,
        "low": 903.22,
        "close": 912.35
      },
      {
        "date": "20260304",
        "open": 912.35,
        "high": 938.57,
        "low": 919.98,
        "close": 929.28
      },
      {
        "date": "20260305",
        "open": 929.28,
        "high": 950.99,
        "low": 932.16,
        "close": 941.58
      },
      {
        "date": "20260306",
        "open": 941.58,
        "high": 938.62,
        "low": 920.03,
        "close": 929.33
      },
      {
        "date": "20260309",
        "open": 929.33,
        "high": 940.92,
        "low": 922.29,
        "close": 931.61
      },
      {
        "date": "20260310",
        "open": 931.61,
        "high": 955.63,
        "low": 936.7,
        "close": 946.17
      },
      {
        "date": "20260311",
        "open": 946.17,
        "high": 940.52,
        "low": 921.89,
        "close": 931.21
      },
      {
        "date": "20260312",
        "open": 931.21,
        "high": 932.08,
        "low": 913.63,
        "close": 922.86
      },
      {
        "date": "20260313",
        "open": 922.86,
        "high": 938.22,
        "low": 919.65,
        "close": 928.94
      },
      {
        "date": "20260316",
        "open": 928.94,
        "high": 942.95,
        "low": 924.28,
        "close": 933.62
      },
      {
        "date": "20260317",
        "open": 933.62,
        "high": 949.21,
        "low": 930.42,
        "close": 939.82
      },
      {
        "date": "20260318",
        "open": 939.82,
        "high": 947.64,
        "low": 928.87,
        "close": 938.26
      },
      {
        "date": "20260319",
        "open": 938.26,
        "high": 939,
        "low": 920.41,
        "close": 929.71
      },
      {
        "date": "20260320",
        "open": 929.71,
        "high": 959.42,
        "low": 940.43,
        "close": 949.93
      }
    ],
    "signal": {
      "currency": "JPYKRW",
      "signal": "BUY",
      "strength": "MODERATE",
      "score": 35,
      "indicators": [
        {
          "name": "RSI(14)",
          "value": 57.44129865092611,
          "signal": "NEUTRAL",
          "description": "중립 (57.4)"
        },
        {
          "name": "EMA(5/20)",
          "value": 4.950098844046124,
          "signal": "BUY",
          "description": "단기 > 장기 (939.0 > 934.0)"
        },
        {
          "name": "MACD(12/26/9)",
          "value": 1.5175165115734046,
          "signal": "BUY",
          "description": "히스토그램 양(+1.52)"
        },
        {
          "name": "Bollinger(20/2)",
          "value": 0.9885086283522999,
          "signal": "SELL",
          "description": "상단 터치 (현재: 949.9, 상단: 950.4)"
        },
        {
          "name": "ADX(14)",
          "value": 8.6307,
          "signal": "NEUTRAL",
          "description": "횡보 (ADX 8.6 < 20) — 추세 신호 신뢰도 낮음"
        },
        {
          "name": "EMA(60) 추세",
          "value": 1.8396970019742127,
          "signal": "BUY",
          "description": "장기 상승 추세 (현재 1.84% > EMA60)"
        },
        {
          "name": "신호 연속성",
          "value": 20,
          "signal": "BUY",
          "description": "전일 방향 일치 (+10)"
        },
        {
          "name": "VIX 공포지수",
          "value": 26.780000686645508,
          "signal": "BUY",
          "description": "리스크 오프 (VIX 26.8) — 외화 강세 우위"
        }
      ],
      "currentRate": 949.93,
      "targetBuy": 925.14,
      "targetSell": 984.64,
      "targetBuyEffective": 941.33,
      "targetSellEffective": 967.41,
      "stopLoss": 935.05,
      "spreadPct": 1.75,
      "effectiveBuyRate": 966.55,
      "effectiveSellRate": 933.31,
      "breakEvenPct": 3.5,
      "netProfitPct": 2.77,
      "calculatedAt": "2026-03-22T18:45:24.740Z"
    },
    "macro": {
      "vix": 26.780000686645508,
      "vixPrev": 25.5,
      "us10y": 4.390999794006348,
      "us10yPrev": 4.136000156402588,
      "fetchedAt": "2026-03-22T18:45:21.555Z"
    },
    "updatedAt": "2026-03-22T18:45:24.740Z"
  },
  {
    "currency": "CNYKRW",
    "rates": [
      {
        "date": "20251217",
        "open": 209.35,
        "high": 211.44,
        "low": 207.25,
        "close": 209.35
      },
      {
        "date": "20251218",
        "open": 209.35,
        "high": 212.34,
        "low": 208.13,
        "close": 210.24
      },
      {
        "date": "20251219",
        "open": 210.24,
        "high": 212.13,
        "low": 207.92,
        "close": 210.03
      },
      {
        "date": "20251222",
        "open": 210.03,
        "high": 212.21,
        "low": 208,
        "close": 210.11
      },
      {
        "date": "20251223",
        "open": 210.11,
        "high": 212.43,
        "low": 208.22,
        "close": 210.33
      },
      {
        "date": "20251224",
        "open": 210.33,
        "high": 213.21,
        "low": 208.98,
        "close": 211.1
      },
      {
        "date": "20251226",
        "open": 211.1,
        "high": 210.45,
        "low": 206.28,
        "close": 208.37
      },
      {
        "date": "20251229",
        "open": 208.37,
        "high": 207.43,
        "low": 203.32,
        "close": 205.38
      },
      {
        "date": "20251230",
        "open": 205.38,
        "high": 206.57,
        "low": 202.48,
        "close": 204.53
      },
      {
        "date": "20251231",
        "open": 204.53,
        "high": 206.8,
        "low": 202.71,
        "close": 204.76
      },
      {
        "date": "20260102",
        "open": 204.76,
        "high": 206.8,
        "low": 202.71,
        "close": 204.76
      },
      {
        "date": "20260105",
        "open": 204.76,
        "high": 208.98,
        "low": 204.85,
        "close": 206.92
      },
      {
        "date": "20260106",
        "open": 206.92,
        "high": 209.59,
        "low": 205.44,
        "close": 207.52
      },
      {
        "date": "20260107",
        "open": 207.52,
        "high": 209.33,
        "low": 205.18,
        "close": 207.26
      },
      {
        "date": "20260108",
        "open": 207.26,
        "high": 209.54,
        "low": 205.39,
        "close": 207.47
      },
      {
        "date": "20260109",
        "open": 207.47,
        "high": 209.33,
        "low": 205.18,
        "close": 207.26
      },
      {
        "date": "20260112",
        "open": 207.26,
        "high": 210.52,
        "low": 206.35,
        "close": 208.44
      },
      {
        "date": "20260113",
        "open": 208.44,
        "high": 212.74,
        "low": 208.53,
        "close": 210.64
      },
      {
        "date": "20260114",
        "open": 210.64,
        "high": 213.36,
        "low": 209.13,
        "close": 211.25
      },
      {
        "date": "20260115",
        "open": 211.25,
        "high": 213.94,
        "low": 209.71,
        "close": 211.83
      },
      {
        "date": "20260116",
        "open": 211.83,
        "high": 213.29,
        "low": 209.06,
        "close": 211.18
      },
      {
        "date": "20260119",
        "open": 211.18,
        "high": 213.74,
        "low": 209.51,
        "close": 211.63
      },
      {
        "date": "20260120",
        "open": 211.63,
        "high": 213.98,
        "low": 209.75,
        "close": 211.87
      },
      {
        "date": "20260121",
        "open": 211.87,
        "high": 214.6,
        "low": 210.35,
        "close": 212.48
      },
      {
        "date": "20260122",
        "open": 212.48,
        "high": 213.54,
        "low": 209.31,
        "close": 211.43
      },
      {
        "date": "20260123",
        "open": 211.43,
        "high": 213.37,
        "low": 209.14,
        "close": 211.26
      },
      {
        "date": "20260126",
        "open": 211.26,
        "high": 213.03,
        "low": 208.82,
        "close": 210.93
      },
      {
        "date": "20260127",
        "open": 210.93,
        "high": 209.28,
        "low": 205.13,
        "close": 207.21
      },
      {
        "date": "20260128",
        "open": 207.21,
        "high": 210.26,
        "low": 206.09,
        "close": 208.18
      },
      {
        "date": "20260129",
        "open": 208.18,
        "high": 207.83,
        "low": 203.72,
        "close": 205.78
      },
      {
        "date": "20260130",
        "open": 205.78,
        "high": 207.51,
        "low": 203.4,
        "close": 205.46
      },
      {
        "date": "20260202",
        "open": 205.46,
        "high": 208.85,
        "low": 204.72,
        "close": 206.79
      },
      {
        "date": "20260203",
        "open": 206.79,
        "high": 211.96,
        "low": 207.77,
        "close": 209.87
      },
      {
        "date": "20260204",
        "open": 209.87,
        "high": 210.98,
        "low": 206.81,
        "close": 208.9
      },
      {
        "date": "20260205",
        "open": 208.9,
        "high": 211.32,
        "low": 207.13,
        "close": 209.23
      },
      {
        "date": "20260206",
        "open": 209.23,
        "high": 212.96,
        "low": 208.75,
        "close": 210.86
      },
      {
        "date": "20260209",
        "open": 210.86,
        "high": 213.93,
        "low": 209.7,
        "close": 211.82
      },
      {
        "date": "20260210",
        "open": 211.82,
        "high": 213.51,
        "low": 209.28,
        "close": 211.4
      },
      {
        "date": "20260211",
        "open": 211.4,
        "high": 212.94,
        "low": 208.73,
        "close": 210.84
      },
      {
        "date": "20260212",
        "open": 210.84,
        "high": 212.76,
        "low": 208.55,
        "close": 210.66
      },
      {
        "date": "20260213",
        "open": 210.66,
        "high": 211.35,
        "low": 207.16,
        "close": 209.26
      },
      {
        "date": "20260219",
        "open": 209.26,
        "high": 211.04,
        "low": 206.87,
        "close": 208.96
      },
      {
        "date": "20260220",
        "open": 208.96,
        "high": 212.34,
        "low": 208.13,
        "close": 210.24
      },
      {
        "date": "20260223",
        "open": 210.24,
        "high": 212.14,
        "low": 207.93,
        "close": 210.04
      },
      {
        "date": "20260224",
        "open": 210.04,
        "high": 211.67,
        "low": 207.48,
        "close": 209.58
      },
      {
        "date": "20260225",
        "open": 209.58,
        "high": 211.89,
        "low": 207.7,
        "close": 209.8
      },
      {
        "date": "20260226",
        "open": 209.8,
        "high": 211.36,
        "low": 207.17,
        "close": 209.27
      },
      {
        "date": "20260227",
        "open": 209.27,
        "high": 209.98,
        "low": 205.83,
        "close": 207.91
      },
      {
        "date": "20260303",
        "open": 207.91,
        "high": 211.6,
        "low": 207.41,
        "close": 209.51
      },
      {
        "date": "20260304",
        "open": 209.51,
        "high": 214.94,
        "low": 210.69,
        "close": 212.82
      },
      {
        "date": "20260305",
        "open": 212.82,
        "high": 215.84,
        "low": 211.57,
        "close": 213.71
      },
      {
        "date": "20260306",
        "open": 213.71,
        "high": 214.82,
        "low": 210.57,
        "close": 212.7
      },
      {
        "date": "20260309",
        "open": 212.7,
        "high": 215.42,
        "low": 211.15,
        "close": 213.29
      },
      {
        "date": "20260310",
        "open": 213.29,
        "high": 217.82,
        "low": 213.51,
        "close": 215.67
      },
      {
        "date": "20260311",
        "open": 215.67,
        "high": 216.07,
        "low": 211.8,
        "close": 213.94
      },
      {
        "date": "20260312",
        "open": 213.94,
        "high": 215.93,
        "low": 211.66,
        "close": 213.8
      },
      {
        "date": "20260313",
        "open": 213.8,
        "high": 217.31,
        "low": 213,
        "close": 215.16
      },
      {
        "date": "20260316",
        "open": 215.16,
        "high": 218.38,
        "low": 214.05,
        "close": 216.22
      },
      {
        "date": "20260317",
        "open": 216.22,
        "high": 219.13,
        "low": 214.8,
        "close": 216.97
      },
      {
        "date": "20260318",
        "open": 216.97,
        "high": 218.9,
        "low": 214.57,
        "close": 216.74
      },
      {
        "date": "20260319",
        "open": 216.74,
        "high": 218.14,
        "low": 213.83,
        "close": 215.99
      },
      {
        "date": "20260320",
        "open": 215.99,
        "high": 219.42,
        "low": 215.07,
        "close": 217.25
      }
    ],
    "signal": {
      "currency": "CNYKRW",
      "signal": "BUY",
      "strength": "MODERATE",
      "score": 30,
      "indicators": [
        {
          "name": "RSI(14)",
          "value": 65.49031506769282,
          "signal": "SELL",
          "description": "약한 과매수 (65.5)"
        },
        {
          "name": "EMA(5/20)",
          "value": 2.566760159585499,
          "signal": "BUY",
          "description": "단기 > 장기 (216.4 > 213.8)"
        },
        {
          "name": "MACD(12/26/9)",
          "value": 0.3618191553728116,
          "signal": "BUY",
          "description": "히스토그램 양(+0.36)"
        },
        {
          "name": "Bollinger(20/2)",
          "value": 0.8602897820594995,
          "signal": "SELL",
          "description": "상단 근접 (위치: 86%)"
        },
        {
          "name": "ADX(14)",
          "value": 20.1838,
          "signal": "NEUTRAL",
          "description": "보통 추세 (ADX 20.2)"
        },
        {
          "name": "EMA(60) 추세",
          "value": 3.158663454153509,
          "signal": "BUY",
          "description": "장기 상승 추세 (현재 3.16% > EMA60)"
        },
        {
          "name": "신호 연속성",
          "value": 5,
          "signal": "BUY",
          "description": "전일 방향 일치 (+10)"
        },
        {
          "name": "VIX 공포지수",
          "value": 26.780000686645508,
          "signal": "BUY",
          "description": "리스크 오프 (VIX 26.8) — 외화 강세 우위"
        }
      ],
      "currentRate": 217.25,
      "targetBuy": 214.28,
      "targetSell": 221.41,
      "targetBuyEffective": 218.56,
      "targetSellEffective": 216.98,
      "stopLoss": 215.47,
      "spreadPct": 2,
      "effectiveBuyRate": 221.59,
      "effectiveSellRate": 212.91,
      "breakEvenPct": 4,
      "netProfitPct": -0.72,
      "calculatedAt": "2026-03-22T18:45:25.821Z"
    },
    "macro": {
      "vix": 26.780000686645508,
      "vixPrev": 25.5,
      "us10y": 4.390999794006348,
      "us10yPrev": 4.136000156402588,
      "fetchedAt": "2026-03-22T18:45:21.555Z"
    },
    "updatedAt": "2026-03-22T18:45:25.821Z"
  },
  {
    "currency": "GBPKRW",
    "rates": [
      {
        "date": "20251217",
        "open": 1976.77,
        "high": 1996.53,
        "low": 1957,
        "close": 1976.77
      },
      {
        "date": "20251218",
        "open": 1976.77,
        "high": 1997.47,
        "low": 1957.92,
        "close": 1977.7
      },
      {
        "date": "20251219",
        "open": 1977.7,
        "high": 1996.62,
        "low": 1957.09,
        "close": 1976.86
      },
      {
        "date": "20251222",
        "open": 1976.86,
        "high": 1997.21,
        "low": 1957.66,
        "close": 1977.44
      },
      {
        "date": "20251223",
        "open": 1977.44,
        "high": 2011.62,
        "low": 1971.79,
        "close": 1991.71
      },
      {
        "date": "20251224",
        "open": 1991.71,
        "high": 2024.63,
        "low": 1984.54,
        "close": 2004.59
      },
      {
        "date": "20251226",
        "open": 2004.59,
        "high": 1992.48,
        "low": 1953.03,
        "close": 1972.76
      },
      {
        "date": "20251229",
        "open": 1972.76,
        "high": 1966.06,
        "low": 1927.13,
        "close": 1946.6
      },
      {
        "date": "20251230",
        "open": 1946.6,
        "high": 1956.2,
        "low": 1917.47,
        "close": 1936.84
      },
      {
        "date": "20251231",
        "open": 1936.84,
        "high": 1951.63,
        "low": 1912.98,
        "close": 1932.31
      },
      {
        "date": "20260102",
        "open": 1932.31,
        "high": 1952.64,
        "low": 1913.97,
        "close": 1933.31
      },
      {
        "date": "20260105",
        "open": 1933.31,
        "high": 1959.6,
        "low": 1920.79,
        "close": 1940.2
      },
      {
        "date": "20260106",
        "open": 1940.2,
        "high": 1978.19,
        "low": 1939.02,
        "close": 1958.61
      },
      {
        "date": "20260107",
        "open": 1958.61,
        "high": 1971.49,
        "low": 1932.46,
        "close": 1951.98
      },
      {
        "date": "20260108",
        "open": 1951.98,
        "high": 1968.68,
        "low": 1929.69,
        "close": 1949.19
      },
      {
        "date": "20260109",
        "open": 1949.19,
        "high": 1967.1,
        "low": 1928.15,
        "close": 1947.63
      },
      {
        "date": "20260112",
        "open": 1947.63,
        "high": 1970.07,
        "low": 1931.06,
        "close": 1950.57
      },
      {
        "date": "20260113",
        "open": 1950.57,
        "high": 1990.97,
        "low": 1951.54,
        "close": 1971.26
      },
      {
        "date": "20260114",
        "open": 1971.26,
        "high": 1997,
        "low": 1957.45,
        "close": 1977.23
      },
      {
        "date": "20260115",
        "open": 1977.23,
        "high": 2005.83,
        "low": 1966.12,
        "close": 1985.98
      },
      {
        "date": "20260116",
        "open": 1985.98,
        "high": 1986.12,
        "low": 1946.79,
        "close": 1966.46
      },
      {
        "date": "20260119",
        "open": 1966.46,
        "high": 1991.11,
        "low": 1951.68,
        "close": 1971.4
      },
      {
        "date": "20260120",
        "open": 1971.4,
        "high": 1997.56,
        "low": 1958.01,
        "close": 1977.79
      },
      {
        "date": "20260121",
        "open": 1977.79,
        "high": 2005.31,
        "low": 1965.6,
        "close": 1985.46
      },
      {
        "date": "20260122",
        "open": 1985.46,
        "high": 1997.67,
        "low": 1958.12,
        "close": 1977.9
      },
      {
        "date": "20260123",
        "open": 1977.9,
        "high": 2003.27,
        "low": 1963.6,
        "close": 1983.44
      },
      {
        "date": "20260126",
        "open": 1983.44,
        "high": 2027.13,
        "low": 1986.98,
        "close": 2007.06
      },
      {
        "date": "20260127",
        "open": 2007.06,
        "high": 1993.26,
        "low": 1953.79,
        "close": 1973.53
      },
      {
        "date": "20260128",
        "open": 1973.53,
        "high": 2024.31,
        "low": 1984.22,
        "close": 2004.27
      },
      {
        "date": "20260129",
        "open": 2004.27,
        "high": 1991.54,
        "low": 1952.11,
        "close": 1971.83
      },
      {
        "date": "20260130",
        "open": 1971.83,
        "high": 1990.32,
        "low": 1950.91,
        "close": 1970.62
      },
      {
        "date": "20260202",
        "open": 1970.62,
        "high": 1982.81,
        "low": 1943.54,
        "close": 1963.18
      },
      {
        "date": "20260203",
        "open": 1963.18,
        "high": 2011.67,
        "low": 1971.84,
        "close": 1991.76
      },
      {
        "date": "20260204",
        "open": 1991.76,
        "high": 2004.83,
        "low": 1965.14,
        "close": 1984.99
      },
      {
        "date": "20260205",
        "open": 1984.99,
        "high": 2000.62,
        "low": 1961.01,
        "close": 1980.82
      },
      {
        "date": "20260206",
        "open": 1980.82,
        "high": 2000.81,
        "low": 1961.19,
        "close": 1981
      },
      {
        "date": "20260209",
        "open": 1981,
        "high": 2019.6,
        "low": 1979.61,
        "close": 1999.61
      },
      {
        "date": "20260210",
        "open": 1999.61,
        "high": 2025.26,
        "low": 1985.15,
        "close": 2005.21
      },
      {
        "date": "20260211",
        "open": 2005.21,
        "high": 2007.08,
        "low": 1967.33,
        "close": 1987.21
      },
      {
        "date": "20260212",
        "open": 1987.21,
        "high": 2000.99,
        "low": 1961.36,
        "close": 1981.18
      },
      {
        "date": "20260213",
        "open": 1981.18,
        "high": 1985.79,
        "low": 1946.46,
        "close": 1966.13
      },
      {
        "date": "20260219",
        "open": 1966.13,
        "high": 1967.37,
        "low": 1928.42,
        "close": 1947.9
      },
      {
        "date": "20260220",
        "open": 1947.9,
        "high": 1973.33,
        "low": 1934.26,
        "close": 1953.8
      },
      {
        "date": "20260223",
        "open": 1953.8,
        "high": 1975.15,
        "low": 1936.04,
        "close": 1955.6
      },
      {
        "date": "20260224",
        "open": 1955.6,
        "high": 1965.36,
        "low": 1926.45,
        "close": 1945.91
      },
      {
        "date": "20260225",
        "open": 1945.91,
        "high": 1970.69,
        "low": 1931.66,
        "close": 1951.18
      },
      {
        "date": "20260226",
        "open": 1951.18,
        "high": 1965.58,
        "low": 1926.65,
        "close": 1946.12
      },
      {
        "date": "20260227",
        "open": 1946.12,
        "high": 1939.78,
        "low": 1901.37,
        "close": 1920.58
      },
      {
        "date": "20260303",
        "open": 1920.58,
        "high": 1943.75,
        "low": 1905.26,
        "close": 1924.51
      },
      {
        "date": "20260304",
        "open": 1924.51,
        "high": 1975.69,
        "low": 1936.56,
        "close": 1956.13
      },
      {
        "date": "20260305",
        "open": 1956.13,
        "high": 1997,
        "low": 1957.45,
        "close": 1977.23
      },
      {
        "date": "20260306",
        "open": 1977.23,
        "high": 1974.83,
        "low": 1935.72,
        "close": 1955.28
      },
      {
        "date": "20260309",
        "open": 1955.28,
        "high": 1983.3,
        "low": 1944.03,
        "close": 1963.67
      },
      {
        "date": "20260310",
        "open": 1963.67,
        "high": 2025.96,
        "low": 1985.85,
        "close": 2005.91
      },
      {
        "date": "20260311",
        "open": 2005.91,
        "high": 1995.44,
        "low": 1955.93,
        "close": 1975.69
      },
      {
        "date": "20260312",
        "open": 1975.69,
        "high": 1984.13,
        "low": 1944.84,
        "close": 1964.49
      },
      {
        "date": "20260313",
        "open": 1964.49,
        "high": 1995.21,
        "low": 1955.7,
        "close": 1975.46
      },
      {
        "date": "20260316",
        "open": 1975.46,
        "high": 1991.89,
        "low": 1952.44,
        "close": 1972.17
      },
      {
        "date": "20260317",
        "open": 1972.17,
        "high": 2011.39,
        "low": 1971.56,
        "close": 1991.48
      },
      {
        "date": "20260318",
        "open": 1991.48,
        "high": 2012.47,
        "low": 1972.62,
        "close": 1992.55
      },
      {
        "date": "20260319",
        "open": 1992.55,
        "high": 1990.06,
        "low": 1950.65,
        "close": 1970.36
      },
      {
        "date": "20260320",
        "open": 1970.36,
        "high": 2034,
        "low": 1993.73,
        "close": 2013.87
      }
    ],
    "signal": {
      "currency": "GBPKRW",
      "signal": "BUY",
      "strength": "MODERATE",
      "score": 35,
      "indicators": [
        {
          "name": "RSI(14)",
          "value": 59.117666704661275,
          "signal": "NEUTRAL",
          "description": "중립 (59.1)"
        },
        {
          "name": "EMA(5/20)",
          "value": 15.157148835711041,
          "signal": "BUY",
          "description": "단기 > 장기 (1990.6 > 1975.5)"
        },
        {
          "name": "MACD(12/26/9)",
          "value": 4.448059535762669,
          "signal": "BUY",
          "description": "히스토그램 양(+4.45)"
        },
        {
          "name": "Bollinger(20/2)",
          "value": 1.0173536741461102,
          "signal": "SELL",
          "description": "상단 터치 (현재: 2013.9, 상단: 2012.3)"
        },
        {
          "name": "ADX(14)",
          "value": 9.7879,
          "signal": "NEUTRAL",
          "description": "횡보 (ADX 9.8 < 20) — 추세 신호 신뢰도 낮음"
        },
        {
          "name": "EMA(60) 추세",
          "value": 2.1791625867932565,
          "signal": "BUY",
          "description": "장기 상승 추세 (현재 2.18% > EMA60)"
        },
        {
          "name": "신호 연속성",
          "value": 20,
          "signal": "BUY",
          "description": "전일 방향 일치 (+10)"
        },
        {
          "name": "VIX 공포지수",
          "value": 26.780000686645508,
          "signal": "BUY",
          "description": "리스크 오프 (VIX 26.8) — 외화 강세 우위"
        }
      ],
      "currentRate": 2013.87,
      "targetBuy": 1962.51,
      "targetSell": 2085.77,
      "targetBuyEffective": 1996.86,
      "targetSellEffective": 2049.27,
      "stopLoss": 1983.06,
      "spreadPct": 1.75,
      "effectiveBuyRate": 2049.11,
      "effectiveSellRate": 1978.63,
      "breakEvenPct": 3.5,
      "netProfitPct": 2.62,
      "calculatedAt": "2026-03-22T18:45:26.854Z"
    },
    "macro": {
      "vix": 26.780000686645508,
      "vixPrev": 25.5,
      "us10y": 4.390999794006348,
      "us10yPrev": 4.136000156402588,
      "fetchedAt": "2026-03-22T18:45:21.555Z"
    },
    "updatedAt": "2026-03-22T18:45:26.854Z"
  },
  {
    "currency": "CADKRW",
    "rates": [
      {
        "date": "20251217",
        "open": 1070.52,
        "high": 1081.22,
        "low": 1059.81,
        "close": 1070.52
      },
      {
        "date": "20251218",
        "open": 1070.52,
        "high": 1083.26,
        "low": 1061.81,
        "close": 1072.54
      },
      {
        "date": "20251219",
        "open": 1072.54,
        "high": 1083.21,
        "low": 1061.76,
        "close": 1072.49
      },
      {
        "date": "20251222",
        "open": 1072.49,
        "high": 1081.93,
        "low": 1060.5,
        "close": 1071.22
      },
      {
        "date": "20251223",
        "open": 1071.22,
        "high": 1086.55,
        "low": 1065.04,
        "close": 1075.8
      },
      {
        "date": "20251224",
        "open": 1075.8,
        "high": 1094.43,
        "low": 1072.76,
        "close": 1083.6
      },
      {
        "date": "20251226",
        "open": 1083.6,
        "high": 1078.8,
        "low": 1057.43,
        "close": 1068.12
      },
      {
        "date": "20251229",
        "open": 1068.12,
        "high": 1065.98,
        "low": 1044.87,
        "close": 1055.43
      },
      {
        "date": "20251230",
        "open": 1055.43,
        "high": 1057.99,
        "low": 1037.04,
        "close": 1047.52
      },
      {
        "date": "20251231",
        "open": 1047.52,
        "high": 1058.19,
        "low": 1037.24,
        "close": 1047.72
      },
      {
        "date": "20260102",
        "open": 1047.72,
        "high": 1056.18,
        "low": 1035.27,
        "close": 1045.73
      },
      {
        "date": "20260105",
        "open": 1045.73,
        "high": 1060.02,
        "low": 1039.03,
        "close": 1049.53
      },
      {
        "date": "20260106",
        "open": 1049.53,
        "high": 1061.11,
        "low": 1040.1,
        "close": 1050.61
      },
      {
        "date": "20260107",
        "open": 1050.61,
        "high": 1057.08,
        "low": 1036.15,
        "close": 1046.62
      },
      {
        "date": "20260108",
        "open": 1046.62,
        "high": 1055.39,
        "low": 1034.5,
        "close": 1044.95
      },
      {
        "date": "20260109",
        "open": 1044.95,
        "high": 1055.97,
        "low": 1035.06,
        "close": 1045.52
      },
      {
        "date": "20260112",
        "open": 1045.52,
        "high": 1056.82,
        "low": 1035.89,
        "close": 1046.36
      },
      {
        "date": "20260113",
        "open": 1046.36,
        "high": 1065.68,
        "low": 1044.57,
        "close": 1055.13
      },
      {
        "date": "20260114",
        "open": 1055.13,
        "high": 1071.16,
        "low": 1049.95,
        "close": 1060.56
      },
      {
        "date": "20260115",
        "open": 1060.56,
        "high": 1075.08,
        "low": 1053.79,
        "close": 1064.44
      },
      {
        "date": "20260116",
        "open": 1064.44,
        "high": 1068.79,
        "low": 1047.62,
        "close": 1058.21
      },
      {
        "date": "20260119",
        "open": 1058.21,
        "high": 1069.75,
        "low": 1048.56,
        "close": 1059.16
      },
      {
        "date": "20260120",
        "open": 1059.16,
        "high": 1073.02,
        "low": 1051.77,
        "close": 1062.4
      },
      {
        "date": "20260121",
        "open": 1062.4,
        "high": 1077.98,
        "low": 1056.63,
        "close": 1067.31
      },
      {
        "date": "20260122",
        "open": 1067.31,
        "high": 1075.22,
        "low": 1053.93,
        "close": 1064.58
      },
      {
        "date": "20260123",
        "open": 1064.58,
        "high": 1075.94,
        "low": 1054.63,
        "close": 1065.29
      },
      {
        "date": "20260126",
        "open": 1065.29,
        "high": 1082.17,
        "low": 1060.74,
        "close": 1071.46
      },
      {
        "date": "20260127",
        "open": 1071.46,
        "high": 1062.81,
        "low": 1041.76,
        "close": 1052.29
      },
      {
        "date": "20260128",
        "open": 1052.29,
        "high": 1076.86,
        "low": 1055.53,
        "close": 1066.2
      },
      {
        "date": "20260129",
        "open": 1066.2,
        "high": 1063.8,
        "low": 1042.73,
        "close": 1053.27
      },
      {
        "date": "20260130",
        "open": 1053.27,
        "high": 1068.51,
        "low": 1047.36,
        "close": 1057.94
      },
      {
        "date": "20260202",
        "open": 1057.94,
        "high": 1062.59,
        "low": 1041.54,
        "close": 1052.07
      },
      {
        "date": "20260203",
        "open": 1052.07,
        "high": 1075.85,
        "low": 1054.54,
        "close": 1065.2
      },
      {
        "date": "20260204",
        "open": 1065.2,
        "high": 1072.74,
        "low": 1051.49,
        "close": 1062.12
      },
      {
        "date": "20260205",
        "open": 1062.12,
        "high": 1072.4,
        "low": 1051.17,
        "close": 1061.79
      },
      {
        "date": "20260206",
        "open": 1061.79,
        "high": 1078.74,
        "low": 1057.37,
        "close": 1068.06
      },
      {
        "date": "20260209",
        "open": 1068.06,
        "high": 1086.2,
        "low": 1064.69,
        "close": 1075.45
      },
      {
        "date": "20260210",
        "open": 1075.45,
        "high": 1090.46,
        "low": 1068.87,
        "close": 1079.67
      },
      {
        "date": "20260211",
        "open": 1079.67,
        "high": 1086.5,
        "low": 1064.99,
        "close": 1075.75
      },
      {
        "date": "20260212",
        "open": 1075.75,
        "high": 1081.97,
        "low": 1060.54,
        "close": 1071.26
      },
      {
        "date": "20260213",
        "open": 1071.26,
        "high": 1071.18,
        "low": 1049.97,
        "close": 1060.58
      },
      {
        "date": "20260219",
        "open": 1060.58,
        "high": 1064.31,
        "low": 1043.24,
        "close": 1053.78
      },
      {
        "date": "20260220",
        "open": 1053.78,
        "high": 1070.86,
        "low": 1049.65,
        "close": 1060.26
      },
      {
        "date": "20260223",
        "open": 1060.26,
        "high": 1070.08,
        "low": 1048.89,
        "close": 1059.49
      },
      {
        "date": "20260224",
        "open": 1059.49,
        "high": 1063.42,
        "low": 1042.37,
        "close": 1052.9
      },
      {
        "date": "20260225",
        "open": 1052.9,
        "high": 1065.84,
        "low": 1044.73,
        "close": 1055.29
      },
      {
        "date": "20260226",
        "open": 1055.29,
        "high": 1060.07,
        "low": 1039.08,
        "close": 1049.58
      },
      {
        "date": "20260227",
        "open": 1049.58,
        "high": 1051.67,
        "low": 1030.84,
        "close": 1041.26
      },
      {
        "date": "20260303",
        "open": 1041.26,
        "high": 1060.18,
        "low": 1039.19,
        "close": 1049.69
      },
      {
        "date": "20260304",
        "open": 1049.69,
        "high": 1081.44,
        "low": 1060.03,
        "close": 1070.74
      },
      {
        "date": "20260305",
        "open": 1070.74,
        "high": 1095,
        "low": 1073.31,
        "close": 1084.16
      },
      {
        "date": "20260306",
        "open": 1084.16,
        "high": 1081.89,
        "low": 1060.46,
        "close": 1071.18
      },
      {
        "date": "20260309",
        "open": 1071.18,
        "high": 1095.75,
        "low": 1074.06,
        "close": 1084.91
      },
      {
        "date": "20260310",
        "open": 1084.91,
        "high": 1110.19,
        "low": 1088.2,
        "close": 1099.2
      },
      {
        "date": "20260311",
        "open": 1099.2,
        "high": 1095.02,
        "low": 1073.33,
        "close": 1084.18
      },
      {
        "date": "20260312",
        "open": 1084.18,
        "high": 1089.72,
        "low": 1068.15,
        "close": 1078.94
      },
      {
        "date": "20260313",
        "open": 1078.94,
        "high": 1096.26,
        "low": 1074.55,
        "close": 1085.41
      },
      {
        "date": "20260316",
        "open": 1085.41,
        "high": 1097.1,
        "low": 1075.37,
        "close": 1086.24
      },
      {
        "date": "20260317",
        "open": 1086.24,
        "high": 1103.89,
        "low": 1082.04,
        "close": 1092.97
      },
      {
        "date": "20260318",
        "open": 1092.97,
        "high": 1100.21,
        "low": 1078.42,
        "close": 1089.32
      },
      {
        "date": "20260319",
        "open": 1089.32,
        "high": 1092.6,
        "low": 1070.97,
        "close": 1081.79
      },
      {
        "date": "20260320",
        "open": 1081.79,
        "high": 1102.75,
        "low": 1080.92,
        "close": 1091.84
      }
    ],
    "signal": {
      "currency": "CADKRW",
      "signal": "BUY",
      "strength": "MODERATE",
      "score": 41,
      "indicators": [
        {
          "name": "RSI(14)",
          "value": 57.86950466286396,
          "signal": "NEUTRAL",
          "description": "중립 (57.9)"
        },
        {
          "name": "EMA(5/20)",
          "value": 9.45883201351171,
          "signal": "BUY",
          "description": "단기 > 장기 (1087.8 > 1078.3)"
        },
        {
          "name": "MACD(12/26/9)",
          "value": 1.304368061762034,
          "signal": "BUY",
          "description": "히스토그램 양(+1.30)"
        },
        {
          "name": "Bollinger(20/2)",
          "value": 0.7719401885803758,
          "signal": "SELL",
          "description": "상단 근접 (위치: 77%)"
        },
        {
          "name": "ADX(14)",
          "value": 14.2497,
          "signal": "NEUTRAL",
          "description": "횡보 (ADX 14.2 < 20) — 추세 신호 신뢰도 낮음"
        },
        {
          "name": "EMA(60) 추세",
          "value": 2.4233817058472145,
          "signal": "BUY",
          "description": "장기 상승 추세 (현재 2.42% > EMA60)"
        },
        {
          "name": "신호 연속성",
          "value": 20,
          "signal": "BUY",
          "description": "전일 방향 일치 (+10)"
        },
        {
          "name": "VIX 공포지수",
          "value": 26.780000686645508,
          "signal": "BUY",
          "description": "리스크 오프 (VIX 26.8) — 외화 강세 우위"
        }
      ],
      "currentRate": 1091.84,
      "targetBuy": 1066.65,
      "targetSell": 1127.11,
      "targetBuyEffective": 1085.32,
      "targetSellEffective": 1107.38,
      "stopLoss": 1076.73,
      "spreadPct": 1.75,
      "effectiveBuyRate": 1110.95,
      "effectiveSellRate": 1072.73,
      "breakEvenPct": 3.5,
      "netProfitPct": 2.03,
      "calculatedAt": "2026-03-22T18:45:27.899Z"
    },
    "macro": {
      "vix": 26.780000686645508,
      "vixPrev": 25.5,
      "us10y": 4.390999794006348,
      "us10yPrev": 4.136000156402588,
      "fetchedAt": "2026-03-22T18:45:21.555Z"
    },
    "updatedAt": "2026-03-22T18:45:27.899Z"
  },
  {
    "currency": "HKDKRW",
    "rates": [
      {
        "date": "20251217",
        "open": 189.27,
        "high": 191.16,
        "low": 187.37,
        "close": 189.27
      },
      {
        "date": "20251218",
        "open": 189.27,
        "high": 191.95,
        "low": 188.14,
        "close": 190.05
      },
      {
        "date": "20251219",
        "open": 190.05,
        "high": 191.73,
        "low": 187.94,
        "close": 189.84
      },
      {
        "date": "20251222",
        "open": 189.84,
        "high": 191.8,
        "low": 188.01,
        "close": 189.91
      },
      {
        "date": "20251223",
        "open": 189.91,
        "high": 191.98,
        "low": 188.17,
        "close": 190.08
      },
      {
        "date": "20251224",
        "open": 190.08,
        "high": 192.63,
        "low": 188.82,
        "close": 190.73
      },
      {
        "date": "20251226",
        "open": 190.73,
        "high": 189.71,
        "low": 185.96,
        "close": 187.84
      },
      {
        "date": "20251229",
        "open": 187.84,
        "high": 187.45,
        "low": 183.74,
        "close": 185.6
      },
      {
        "date": "20251230",
        "open": 185.6,
        "high": 186.3,
        "low": 182.61,
        "close": 184.46
      },
      {
        "date": "20251231",
        "open": 184.46,
        "high": 186.25,
        "low": 182.56,
        "close": 184.41
      },
      {
        "date": "20260102",
        "open": 184.41,
        "high": 186.15,
        "low": 182.46,
        "close": 184.31
      },
      {
        "date": "20260105",
        "open": 184.31,
        "high": 186.94,
        "low": 183.23,
        "close": 185.09
      },
      {
        "date": "20260106",
        "open": 185.09,
        "high": 187.69,
        "low": 183.98,
        "close": 185.84
      },
      {
        "date": "20260107",
        "open": 185.84,
        "high": 187.49,
        "low": 183.78,
        "close": 185.64
      },
      {
        "date": "20260108",
        "open": 185.64,
        "high": 187.84,
        "low": 184.13,
        "close": 185.99
      },
      {
        "date": "20260109",
        "open": 185.99,
        "high": 187.88,
        "low": 184.15,
        "close": 186.02
      },
      {
        "date": "20260112",
        "open": 186.02,
        "high": 188.6,
        "low": 184.87,
        "close": 186.74
      },
      {
        "date": "20260113",
        "open": 186.74,
        "high": 189.68,
        "low": 185.93,
        "close": 187.81
      },
      {
        "date": "20260114",
        "open": 187.81,
        "high": 190.69,
        "low": 186.92,
        "close": 188.81
      },
      {
        "date": "20260115",
        "open": 188.81,
        "high": 191.38,
        "low": 187.59,
        "close": 189.49
      },
      {
        "date": "20260116",
        "open": 189.49,
        "high": 190.36,
        "low": 186.59,
        "close": 188.48
      },
      {
        "date": "20260119",
        "open": 188.48,
        "high": 190.84,
        "low": 187.07,
        "close": 188.96
      },
      {
        "date": "20260120",
        "open": 188.96,
        "high": 190.89,
        "low": 187.11,
        "close": 189
      },
      {
        "date": "20260121",
        "open": 189,
        "high": 191.27,
        "low": 187.48,
        "close": 189.38
      },
      {
        "date": "20260122",
        "open": 189.38,
        "high": 190.77,
        "low": 187,
        "close": 188.89
      },
      {
        "date": "20260123",
        "open": 188.89,
        "high": 190.22,
        "low": 186.45,
        "close": 188.34
      },
      {
        "date": "20260126",
        "open": 188.34,
        "high": 190.07,
        "low": 186.3,
        "close": 188.19
      },
      {
        "date": "20260127",
        "open": 188.19,
        "high": 186.89,
        "low": 183.18,
        "close": 185.04
      },
      {
        "date": "20260128",
        "open": 185.04,
        "high": 187.61,
        "low": 183.9,
        "close": 185.76
      },
      {
        "date": "20260129",
        "open": 185.76,
        "high": 184.94,
        "low": 181.27,
        "close": 183.11
      },
      {
        "date": "20260130",
        "open": 183.11,
        "high": 184.63,
        "low": 180.98,
        "close": 182.81
      },
      {
        "date": "20260202",
        "open": 182.81,
        "high": 185.73,
        "low": 182.06,
        "close": 183.9
      },
      {
        "date": "20260203",
        "open": 183.9,
        "high": 188.42,
        "low": 184.69,
        "close": 186.56
      },
      {
        "date": "20260204",
        "open": 186.56,
        "high": 187.31,
        "low": 183.6,
        "close": 185.46
      },
      {
        "date": "20260205",
        "open": 185.46,
        "high": 187.61,
        "low": 183.9,
        "close": 185.76
      },
      {
        "date": "20260206",
        "open": 185.76,
        "high": 189.24,
        "low": 185.49,
        "close": 187.37
      },
      {
        "date": "20260209",
        "open": 187.37,
        "high": 190.06,
        "low": 186.29,
        "close": 188.18
      },
      {
        "date": "20260210",
        "open": 188.18,
        "high": 189.23,
        "low": 185.48,
        "close": 187.36
      },
      {
        "date": "20260211",
        "open": 187.36,
        "high": 188.31,
        "low": 184.58,
        "close": 186.45
      },
      {
        "date": "20260212",
        "open": 186.45,
        "high": 187.94,
        "low": 184.21,
        "close": 186.08
      },
      {
        "date": "20260213",
        "open": 186.08,
        "high": 186.51,
        "low": 182.82,
        "close": 184.67
      },
      {
        "date": "20260219",
        "open": 184.67,
        "high": 186.52,
        "low": 182.83,
        "close": 184.68
      },
      {
        "date": "20260220",
        "open": 184.68,
        "high": 187.49,
        "low": 183.78,
        "close": 185.64
      },
      {
        "date": "20260223",
        "open": 185.64,
        "high": 187.25,
        "low": 183.54,
        "close": 185.4
      },
      {
        "date": "20260224",
        "open": 185.4,
        "high": 186.26,
        "low": 182.57,
        "close": 184.42
      },
      {
        "date": "20260225",
        "open": 184.42,
        "high": 186.66,
        "low": 182.97,
        "close": 184.82
      },
      {
        "date": "20260226",
        "open": 184.82,
        "high": 185.38,
        "low": 181.71,
        "close": 183.55
      },
      {
        "date": "20260227",
        "open": 183.55,
        "high": 183.9,
        "low": 180.25,
        "close": 182.08
      },
      {
        "date": "20260303",
        "open": 182.08,
        "high": 185.35,
        "low": 181.68,
        "close": 183.52
      },
      {
        "date": "20260304",
        "open": 183.52,
        "high": 189.51,
        "low": 185.76,
        "close": 187.64
      },
      {
        "date": "20260305",
        "open": 187.64,
        "high": 191.06,
        "low": 187.27,
        "close": 189.17
      },
      {
        "date": "20260306",
        "open": 189.17,
        "high": 189.14,
        "low": 185.39,
        "close": 187.27
      },
      {
        "date": "20260309",
        "open": 187.27,
        "high": 190.37,
        "low": 186.6,
        "close": 188.49
      },
      {
        "date": "20260310",
        "open": 188.49,
        "high": 192.82,
        "low": 189.01,
        "close": 190.92
      },
      {
        "date": "20260311",
        "open": 190.92,
        "high": 190.13,
        "low": 186.36,
        "close": 188.25
      },
      {
        "date": "20260312",
        "open": 188.25,
        "high": 189.37,
        "low": 185.62,
        "close": 187.5
      },
      {
        "date": "20260313",
        "open": 187.5,
        "high": 190.96,
        "low": 187.17,
        "close": 189.07
      },
      {
        "date": "20260316",
        "open": 189.07,
        "high": 192.19,
        "low": 188.38,
        "close": 190.29
      },
      {
        "date": "20260317",
        "open": 190.29,
        "high": 192.96,
        "low": 189.13,
        "close": 191.05
      },
      {
        "date": "20260318",
        "open": 191.05,
        "high": 192.24,
        "low": 188.43,
        "close": 190.34
      },
      {
        "date": "20260319",
        "open": 190.34,
        "high": 191.48,
        "low": 187.69,
        "close": 189.59
      },
      {
        "date": "20260320",
        "open": 189.59,
        "high": 193.36,
        "low": 189.53,
        "close": 191.45
      }
    ],
    "signal": {
      "currency": "HKDKRW",
      "signal": "BUY",
      "strength": "MODERATE",
      "score": 32,
      "indicators": [
        {
          "name": "RSI(14)",
          "value": 60.0632612328982,
          "signal": "SELL",
          "description": "약한 과매수 (60.1)"
        },
        {
          "name": "EMA(5/20)",
          "value": 1.9414116459499269,
          "signal": "BUY",
          "description": "단기 > 장기 (190.4 > 188.4)"
        },
        {
          "name": "MACD(12/26/9)",
          "value": 0.40525860603904007,
          "signal": "BUY",
          "description": "히스토그램 양(+0.41)"
        },
        {
          "name": "Bollinger(20/2)",
          "value": 0.8557261120580217,
          "signal": "SELL",
          "description": "상단 근접 (위치: 86%)"
        },
        {
          "name": "ADX(14)",
          "value": 15.1842,
          "signal": "NEUTRAL",
          "description": "횡보 (ADX 15.2 < 20) — 추세 신호 신뢰도 낮음"
        },
        {
          "name": "EMA(60) 추세",
          "value": 2.239829995513982,
          "signal": "BUY",
          "description": "장기 상승 추세 (현재 2.24% > EMA60)"
        },
        {
          "name": "신호 연속성",
          "value": 20,
          "signal": "BUY",
          "description": "전일 방향 일치 (+10)"
        },
        {
          "name": "VIX 공포지수",
          "value": 26.780000686645508,
          "signal": "BUY",
          "description": "리스크 오프 (VIX 26.8) — 외화 강세 우위"
        }
      ],
      "currentRate": 191.45,
      "targetBuy": 187.32,
      "targetSell": 197.24,
      "targetBuyEffective": 191.06,
      "targetSellEffective": 193.29,
      "stopLoss": 188.97,
      "spreadPct": 2,
      "effectiveBuyRate": 195.28,
      "effectiveSellRate": 187.62,
      "breakEvenPct": 4,
      "netProfitPct": 1.17,
      "calculatedAt": "2026-03-22T18:45:28.976Z"
    },
    "macro": {
      "vix": 26.780000686645508,
      "vixPrev": 25.5,
      "us10y": 4.390999794006348,
      "us10yPrev": 4.136000156402588,
      "fetchedAt": "2026-03-22T18:45:21.555Z"
    },
    "updatedAt": "2026-03-22T18:45:28.976Z"
  }
]